Workbook

Sheet Assumptions
A1: SOULGAINZ · Financial Model Assumptions (USD)
A2: Assumption | B2: Value | C2: Unit | D2: Notes
A3: PRICING (USD)
A4: Monthly Pro price | B4: 16.99 | C4: USD/mo | D4: Stripe live price — change here if you update Stripe
A5: Annual Pro price | B5: 150 | C5: USD/yr | D5: $12.50/mo effective · saves $53.88 vs monthly
A6: Stripe fee (blended %) | B6: 0.029 | C6: % | D6: 2.9% — standard Stripe rate
A7: Stripe fixed fee | B7: 0.3 | C7: USD | D7: Per transaction
A8: SUBSCRIBER MIX
A9: Monthly : Annual split | B9: 0.6 | C9: % monthly | D9: 60% monthly, 40% annual
A10: Free-to-paid conversion | B10: 0.04 | C10: % | D10: 4% — fitness app benchmark
A11: CHURN
A12: Monthly sub churn | B12: 0.06 | C12: %/mo | D12: 6%/mo = ~52% annual — fitness app average
A13: Annual renewal rate | B13: 0.78 | C13: % | D13: 78% renew · 22% annual churn
A14: USER ACQUISITION — BASE CASE
A15: Month 1 new free signups | B15: 80 | C15: users | D15: Waitlist + launch organic traffic
A16: Monthly signup growth (MoM) | B16: 0.15 | C16: %/mo | D16: 15% — SEO, word of mouth, Instagram
A17: ACTUAL MONTHLY COSTS (USD)
A18: Claude Pro subscription | B18: 19.2 | C18: USD/mo | D18: QAR 69.99 × 0.274 exchange rate
A19: Netlify Pro | B19: 19 | C19: USD/mo | D19: Functions + custom domain + bandwidth
A20: Supabase | B20: 0 | C20: USD/mo | D20: Free tier (upgrade at scale)
A21: Apple Developer Program | B21: 8.25 | C21: USD/mo | D21: $99 USD/yr ÷ 12 (pending enrollment)
A22: Google Play | B22: 0 | C22: USD/mo | D22: $25 one-time — already paid ✅
A23: Google Domains (soulgainz.app) | B23: 1 | C23: USD/mo | D23: ~$12/yr — .app domain
A24: Resend email | B24: 0 | C24: USD/mo | D24: Free tier (3,000 emails/day)
A25: Sentry error tracking | B25: 0 | C25: USD/mo | D25: Free tier
A26: Misc / buffer | B26: 10 | C26: USD/mo | D26: Testing, tools, ad experiments
A27: SUNK BUILD COSTS (USD)
A28: Dev hours (estimated) | B28: 400 | C28: hours | D28: Claude-assisted development
A29: Market rate | B29: 80 | C29: USD/hr | D29: Mid-level full-stack, est. USD rate
A30: Implied sweat equity | B30: 32000 | C30: USD | D30: Hours × rate — sunk cost, not cash
A31: Google Play one-time | B31: 25 | C31: USD | D31: Already paid ✅
A32: Apple Developer (yr 1) | B32: 99 | C32: USD | D32: Pending ⏳
A33: Domain registration | B33: 12 | C33: USD | D33: Already registered ✅
A34: Total cash out-of-pocket | B34: 136 | C34: USD | D34: =Google Play + Apple + Domain

Sheet Revenue Model
A1: SOULGAINZ · 24-Month Revenue Model (USD, Base Case)
A2: Metric | B2: M1 | C2: M2 | D2: M3 | E2: M4 | F2: M5 | G2: M6 | H2: M7 | I2: M8 | J2: M9 | K2: M10 | L2: M11 | M2: M12 | N2: M13 | O2: M14 | P2: M15 | Q2: M16 | R2: M17 | S2: M18 | T2: M19 | U2: M20 | V2: M21 | W2: M22 | X2: M23 | Y2: M24
A3: FREE USERS
A4: New signups | B4: ='Assumptions'!B15 | C4: =ROUND(B4*(1+'Assumptions'!B16),0) | D4: =ROUND(C4*(1+'Assumptions'!B16),0) | E4: =ROUND(D4*(1+'Assumptions'!B16),0) | F4: =ROUND(E4*(1+'Assumptions'!B16),0) | G4: =ROUND(F4*(1+'Assumptions'!B16),0) | H4: =ROUND(G4*(1+'Assumptions'!B16),0) | I4: =ROUND(H4*(1+'Assumptions'!B16),0) | J4: =ROUND(I4*(1+'Assumptions'!B16),0) | K4: =ROUND(J4*(1+'Assumptions'!B16),0) | L4: =ROUND(K4*(1+'Assumptions'!B16),0) | M4: =ROUND(L4*(1+'Assumptions'!B16),0) | N4: =ROUND(M4*(1+'Assumptions'!B16),0) | O4: =ROUND(N4*(1+'Assumptions'!B16),0) | P4: =ROUND(O4*(1+'Assumptions'!B16),0) | Q4: =ROUND(P4*(1+'Assumptions'!B16),0) | R4: =ROUND(Q4*(1+'Assumptions'!B16),0) | S4: =ROUND(R4*(1+'Assumptions'!B16),0) | T4: =ROUND(S4*(1+'Assumptions'!B16),0) | U4: =ROUND(T4*(1+'Assumptions'!B16),0) | V4: =ROUND(U4*(1+'Assumptions'!B16),0) | W4: =ROUND(V4*(1+'Assumptions'!B16),0) | X4: =ROUND(W4*(1+'Assumptions'!B16),0) | Y4: =ROUND(X4*(1+'Assumptions'!B16),0)
A5: Cumulative free users | B5: =B4 | C5: =IFERROR(B5+C4-C7,0) | D5: =IFERROR(C5+D4-D7,0) | E5: =IFERROR(D5+E4-E7,0) | F5: =IFERROR(E5+F4-F7,0) | G5: =IFERROR(F5+G4-G7,0) | H5: =IFERROR(G5+H4-H7,0) | I5: =IFERROR(H5+I4-I7,0) | J5: =IFERROR(I5+J4-J7,0) | ... Y5: =IFERROR(X5+Y4-Y7,0)
A6: SUBSCRIBERS
A7: New paid converts | B7: =ROUND(B4*'Assumptions'!B10,0) | C7: =ROUND(C4*'Assumptions'!B10,0) | D7: =ROUND(D4*'Assumptions'!B10,0) | E7: =ROUND(E4*'Assumptions'!B10,0) | F7: =ROUND(F4*'Assumptions'!B10,0) | G7: =ROUND(G4*'Assumptions'!B10,0) | H7: =ROUND(H4*'Assumptions'!B10,0) | I7: =ROUND(I4*'Assumptions'!B10,0) | J7: =ROUND(J4*'Assumptions'!B10,0) | K7: =ROUND(K4*'Assumptions'!B10,0) | L7: =ROUND(L4*'Assumptions'!B10,0) | M7: =ROUND(M4*'Assumptions'!B10,0) | N7: =ROUND(N4*'Assumptions'!B10,0) | O7: =ROUND(O4*'Assumptions'!B10,0) | P7: =ROUND(P4*'Assumptions'!B10,0) | Q7: =ROUND(Q4*'Assumptions'!B10,0) | R7: =ROUND(R4*'Assumptions'!B10,0) | S7: =ROUND(S4*'Assumptions'!B10,0) | T7: =ROUND(T4*'Assumptions'!B10,0) | U7: =ROUND(U4*'Assumptions'!B10,0) | V7: =ROUND(V4*'Assumptions'!B10,0) | W7: =ROUND(W4*'Assumptions'!B10,0) | X7: =ROUND(X4*'Assumptions'!B10,0) | Y7: =ROUND(Y4*'Assumptions'!B10,0)
A8: Monthly subs (active) | B8: =ROUND(B7*'Assumptions'!B9,0) | C8: =ROUND((B8+C7*'Assumptions'!B9)*(1-'Assumptions'!B12),0) | D8: =ROUND((C8+D7*'Assumptions'!B9)*(1-'Assumptions'!B12),0) | E8: =ROUND((D8+E7*'Assumptions'!B9)*(1-'Assumptions'!B12),0) | F8: =ROUND((E8+F7*'Assumptions'!B9)*(1-'Assumptions'!B12),0) | G8: =ROUND((F8+G7*'Assumptions'!B9)*(1-'Assumptions'!B12),0) | H8: =ROUND((G8+H7*'Assumptions'!B9)*(1-'Assumptions'!B12),0) | I8: =ROUND((H8+I7*'Assumptions'!B9)*(1-'Assumptions'!B12),0) | J8: =ROUND((I8+J7*'Assumptions'!B9)*(1-'Assumptions'!B12),0) | K8: =ROUND((J8+K7*'Assumptions'!B9)*(1-'Assumptions'!B12),0) | L8: =ROUND((K8+L7*'Assumptions'!B9)*(1-'Assumptions'!B12),0) | M8: =ROUND((L8+M7*'Assumptions'!B9)*(1-'Assumptions'!B12),0) | N8: =ROUND((M8+N7*'Assumptions'!B9)*(1-'Assumptions'!B12),0) | O8: =ROUND((N8+O7*'Assumptions'!B9)*(1-'Assumptions'!B12),0) | P8: =ROUND((O8+P7*'Assumptions'!B9)*(1-'Assumptions'!B12),0) | Q8: =ROUND((P8+Q7*'Assumptions'!B9)*(1-'Assumptions'!B12),0) | R8: =ROUND((Q8+R7*'Assumptions'!B9)*(1-'Assumptions'!B12),0) | S8: =ROUND((R8+S7*'Assumptions'!B9)*(1-'Assumptions'!B12),0) | T8: =ROUND((S8+T7*'Assumptions'!B9)*(1-'Assumptions'!B12),0) | U8: =ROUND((T8+U7*'Assumptions'!B9)*(1-'Assumptions'!B12),0) | V8: =ROUND((U8+V7*'Assumptions'!B9)*(1-'Assumptions'!B12),0) | W8: =ROUND((V8+W7*'Assumptions'!B9)*(1-'Assumptions'!B12),0) | X8: =ROUND((W8+X7*'Assumptions'!B9)*(1-'Assumptions'!B12),0) | Y8: =ROUND((X8+Y7*'Assumptions'!B9)*(1-'Assumptions'!B12),0)
A9: Annual subs (active) | B9: =ROUND(B7*(1-'Assumptions'!B9),0) | C9: =ROUND(B9*(1-(1-'Assumptions'!B13)/12)+C7*(1-'Assumptions'!B9),0) | D9: =ROUND(C9*(1-(1-'Assumptions'!B13)/12)+D7*(1-'Assumptions'!B9),0) | E9: =ROUND(D9*(1-(1-'Assumptions'!B13)/12)+E7*(1-'Assumptions'!B9),0) | F9: =ROUND(E9*(1-(1-'Assumptions'!B13)/12)+F7*(1-'Assumptions'!B9),0) | G9: =ROUND(F9*(1-(1-'Assumptions'!B13)/12)+G7*(1-'Assumptions'!B9),0) | H9: =ROUND(G9*(1-(1-'Assumptions'!B13)/12)+H7*(1-'Assumptions'!B9),0) | I9: =ROUND(H9*(1-(1-'Assumptions'!B13)/12)+I7*(1-'Assumptions'!B9),0) | J9: =ROUND(I9*(1-(1-'Assumptions'!B13)/12)+J7*(1-'Assumptions'!B9),0) | K9: =ROUND(J9*(1-(1-'Assumptions'!B13)/12)+K7*(1-'Assumptions'!B9),0) | L9: =ROUND(K9*(1-(1-'Assumptions'!B13)/12)+L7*(1-'Assumptions'!B9),0) | M9: =ROUND(L9*(1-(1-'Assumptions'!B13)/12)+M7*(1-'Assumptions'!B9),0) | N9: =ROUND(M9*(1-(1-'Assumptions'!B13)/12)+N7*(1-'Assumptions'!B9),0) | O9: =ROUND(N9*(1-(1-'Assumptions'!B13)/12)+O7*(1-'Assumptions'!B9),0) | P9: =ROUND(O9*(1-(1-'Assumptions'!B13)/12)+P7*(1-'Assumptions'!B9),0) | Q9: =ROUND(P9*(1-(1-'Assumptions'!B13)/12)+Q7*(1-'Assumptions'!B9),0) | R9: =ROUND(Q9*(1-(1-'Assumptions'!B13)/12)+R7*(1-'Assumptions'!B9),0) | S9: =ROUND(R9*(1-(1-'Assumptions'!B13)/12)+S7*(1-'Assumptions'!B9),0) | T9: =ROUND(S9*(1-(1-'Assumptions'!B13)/12)+T7*(1-'Assumptions'!B9),0) | U9: =ROUND(T9*(1-(1-'Assumptions'!B13)/12)+U7*(1-'Assumptions'!B9),0) | V9: =ROUND(U9*(1-(1-'Assumptions'!B13)/12)+V7*(1-'Assumptions'!B9),0) | W9: =ROUND(V9*(1-(1-'Assumptions'!B13)/12)+W7*(1-'Assumptions'!B9),0) | X9: =ROUND(W9*(1-(1-'Assumptions'!B13)/12)+X7*(1-'Assumptions'!B9),0) | Y9: =ROUND(X9*(1-(1-'Assumptions'!B13)/12)+Y7*(1-'Assumptions'!B9),0)
A10: Total paying users | B10: =B8+B9 | C10: =C8+C9 | D10: =D8+D9 | E10: =E8+E9 | F10: =F8+F9 | G10: =G8+G9 | H10: =H8+H9 | I10: =I8+I9 | ... Y10: =Y8+Y9
A11: REVENUE
A12: Monthly sub revenue | B12: =B8*'Assumptions'!B4 | C12: =C8*'Assumptions'!B4 | D12: =D8*'Assumptions'!B4 | E12: =E8*'Assumptions'!B4 | F12: =F8*'Assumptions'!B4 | G12: =G8*'Assumptions'!B4 | H12: =H8*'Assumptions'!B4 | I12: =I8*'Assumptions'!B4 | J12: =J8*'Assumptions'!B4 | K12: =K8*'Assumptions'!B4 | L12: =L8*'Assumptions'!B4 | M12: =M8*'Assumptions'!B4 | N12: =N8*'Assumptions'!B4 | O12: =O8*'Assumptions'!B4 | P12: =P8*'Assumptions'!B4 | Q12: =Q8*'Assumptions'!B4 | R12: =R8*'Assumptions'!B4 | S12: =S8*'Assumptions'!B4 | T12: =T8*'Assumptions'!B4 | U12: =U8*'Assumptions'!B4 | V12: =V8*'Assumptions'!B4 | W12: =W8*'Assumptions'!B4 | X12: =X8*'Assumptions'!B4 | Y12: =Y8*'Assumptions'!B4
A13: Annual sub revenue (1/12) | B13: =B9*'Assumptions'!B5/12 | C13: =C9*'Assumptions'!B5/12 | D13: =D9*'Assumptions'!B5/12 | E13: =E9*'Assumptions'!B5/12 | F13: =F9*'Assumptions'!B5/12 | G13: =G9*'Assumptions'!B5/12 | H13: =H9*'Assumptions'!B5/12 | I13: =I9*'Assumptions'!B5/12 | J13: =J9*'Assumptions'!B5/12 | K13: =K9*'Assumptions'!B5/12 | L13: =L9*'Assumptions'!B5/12 | M13: =M9*'Assumptions'!B5/12 | N13: =N9*'Assumptions'!B5/12 | O13: =O9*'Assumptions'!B5/12 | P13: =P9*'Assumptions'!B5/12 | Q13: =Q9*'Assumptions'!B5/12 | R13: =R9*'Assumptions'!B5/12 | S13: =S9*'Assumptions'!B5/12 | T13: =T9*'Assumptions'!B5/12 | U13: =U9*'Assumptions'!B5/12 | V13: =V9*'Assumptions'!B5/12 | W13: =W9*'Assumptions'!B5/12 | X13: =X9*'Assumptions'!B5/12 | Y13: =Y9*'Assumptions'!B5/12
A14: Gross revenue | B14: =B12+B13 | C14: =C12+C13 | D14: =D12+D13 | E14: =E12+E13 | F14: =F12+F13 | G14: =G12+G13 | H14: =H12+H13 | I14: =I12+I13 | ... Y14: =Y12+Y13
A15: Stripe fees | B15: =-(B14*'Assumptions'!B6+'Assumptions'!B7*B10) | C15: =-(C14*'Assumptions'!B6+'Assumptions'!B7*C10) | D15: =-(D14*'Assumptions'!B6+'Assumptions'!B7*D10) | E15: =-(E14*'Assumptions'!B6+'Assumptions'!B7*E10) | F15: =-(F14*'Assumptions'!B6+'Assumptions'!B7*F10) | G15: =-(G14*'Assumptions'!B6+'Assumptions'!B7*G10) | H15: =-(H14*'Assumptions'!B6+'Assumptions'!B7*H10) | I15: =-(I14*'Assumptions'!B6+'Assumptions'!B7*I10) | J15: =-(J14*'Assumptions'!B6+'Assumptions'!B7*J10) | K15: =-(K14*'Assumptions'!B6+'Assumptions'!B7*K10) | L15: =-(L14*'Assumptions'!B6+'Assumptions'!B7*L10) | M15: =-(M14*'Assumptions'!B6+'Assumptions'!B7*M10) | N15: =-(N14*'Assumptions'!B6+'Assumptions'!B7*N10) | O15: =-(O14*'Assumptions'!B6+'Assumptions'!B7*O10) | P15: =-(P14*'Assumptions'!B6+'Assumptions'!B7*P10) | Q15: =-(Q14*'Assumptions'!B6+'Assumptions'!B7*Q10) | R15: =-(R14*'Assumptions'!B6+'Assumptions'!B7*R10) | S15: =-(S14*'Assumptions'!B6+'Assumptions'!B7*S10) | T15: =-(T14*'Assumptions'!B6+'Assumptions'!B7*T10) | U15: =-(U14*'Assumptions'!B6+'Assumptions'!B7*U10) | V15: =-(V14*'Assumptions'!B6+'Assumptions'!B7*V10) | W15: =-(W14*'Assumptions'!B6+'Assumptions'!B7*W10) | X15: =-(X14*'Assumptions'!B6+'Assumptions'!B7*X10) | Y15: =-(Y14*'Assumptions'!B6+'Assumptions'!B7*Y10)
A16: Net revenue | B16: =B14+B15 | C16: =C14+C15 | D16: =D14+D15 | E16: =E14+E15 | F16: =F14+F15 | G16: =G14+G15 | H16: =H14+H15 | I16: =I14+I15 | ... Y16: =Y14+Y15
A17: COSTS
A18: Fixed monthly costs | B18: =-('Assumptions'!B18+'Assumptions'!B19+'Assumptions'!B20+'Assumptions'!B21+'Assumptions'!B22+'Assumptions'!B23+'Assumptions'!B24+'Assumptions'!B25+'Assumptions'!B26) | C18: =-('Assumptions'!B18+'Assumptions'!B19+'Assumptions'!B20+'Assumptions'!B21+'Assumptions'!B22+'Assumptions'!B23+'Assumptions'!B24+'Assumptions'!B25+'Assumptions'!B26) | D18: =-('Assumptions'!B18+'Assumptions'!B19+'Assumptions'!B20+'Assumptions'!B21+'Assumptions'!B22+'Assumptions'!B23+'Assumptions'!B24+'Assumptions'!B25+'Assumptions'!B26) | E18: =-('Assumptions'!B18+'Assumptions'!B19+'Assumptions'!B20+'Assumptions'!B21+'Assumptions'!B22+'Assumptions'!B23+'Assumptions'!B24+'Assumptions'!B25+'Assumptions'!B26) | F18: =-('Assumptions'!B18+'Assumptions'!B19+'Assumptions'!B20+'Assumptions'!B21+'Assumptions'!B22+'Assumptions'!B23+'Assumptions'!B24+'Assumptions'!B25+'Assumptions'!B26) | G18: =-('Assumptions'!B18+'Assumptions'!B19+'Assumptions'!B20+'Assumptions'!B21+'Assumptions'!B22+'Assumptions'!B23+'Assumptions'!B24+'Assumptions'!B25+'Assumptions'!B26) | H18: =-('Assumptions'!B18+'Assumptions'!B19+'Assumptions'!B20+'Assumptions'!B21+'Assumptions'!B22+'Assumptions'!B23+'Assumptions'!B24+'Assumptions'!B25+'Assumptions'!B26) | I18: =-('Assumptions'!B18+'Assumptions'!B19+'Assumptions'!B20+'Assumptions'!B21+'Assumptions'!B22+'Assumptions'!B23+'Assumptions'!B24+'Assumptions'!B25+'Assumptions'!B26) | J18: =-('Assumptions'!B18+'Assumptions'!B19+'Assumptions'!B20+'Assumptions'!B21+'Assumptions'!B22+'Assumptions'!B23+'Assumptions'!B24+'Assumptions'!B25+'Assumptions'!B26) | K18: =-('Assumptions'!B18+'Assumptions'!B19+'Assumptions'!B20+'Assumptions'!B21+'Assumptions'!B22+'Assumptions'!B23+'Assumptions'!B24+'Assumptions'!B25+'Assumptions'!B26) | L18: =-('Assumptions'!B18+'Assumptions'!B19+'Assumptions'!B20+'Assumptions'!B21+'Assumptions'!B22+'Assumptions'!B23+'Assumptions'!B24+'Assumptions'!B25+'Assumptions'!B26) | M18: =-('Assumptions'!B18+'Assumptions'!B19+'Assumptions'!B20+'Assumptions'!B21+'Assumptions'!B22+'Assumptions'!B23+'Assumptions'!B24+'Assumptions'!B25+'Assumptions'!B26) | N18: =-('Assumptions'!B18+'Assumptions'!B19+'Assumptions'!B20+'Assumptions'!B21+'Assumptions'!B22+'Assumptions'!B23+'Assumptions'!B24+'Assumptions'!B25+'Assumptions'!B26) | O18: =-('Assumptions'!B18+'Assumptions'!B19+'Assumptions'!B20+'Assumptions'!B21+'Assumptions'!B22+'Assumptions'!B23+'Assumptions'!B24+'Assumptions'!B25+'Assumptions'!B26) | P18: =-('Assumptions'!B18+'Assumptions'!B19+'Assumptions'!B20+'Assumptions'!B21+'Assumptions'!B22+'Assumptions'!B23+'Assumptions'!B24+'Assumptions'!B25+'Assumptions'!B26) | Q18: =-('Assumptions'!B18+'Assumptions'!B19+'Assumptions'!B20+'Assumptions'!B21+'Assumptions'!B22+'Assumptions'!B23+'Assumptions'!B24+'Assumptions'!B25+'Assumptions'!B26) | R18: =-('Assumptions'!B18+'Assumptions'!B19+'Assumptions'!B20+'Assumptions'!B21+'Assumptions'!B22+'Assumptions'!B23+'Assumptions'!B24+'Assumptions'!B25+'Assumptions'!B26) | S18: =-('Assumptions'!B18+'Assumptions'!B19+'Assumptions'!B20+'Assumptions'!B21+'Assumptions'!B22+'Assumptions'!B23+'Assumptions'!B24+'Assumptions'!B25+'Assumptions'!B26) | T18: =-('Assumptions'!B18+'Assumptions'!B19+'Assumptions'!B20+'Assumptions'!B21+'Assumptions'!B22+'Assumptions'!B23+'Assumptions'!B24+'Assumptions'!B25+'Assumptions'!B26) | U18: =-('Assumptions'!B18+'Assumptions'!B19+'Assumptions'!B20+'Assumptions'!B21+'Assumptions'!B22+'Assumptions'!B23+'Assumptions'!B24+'Assumptions'!B25+'Assumptions'!B26) | V18: =-('Assumptions'!B18+'Assumptions'!B19+'Assumptions'!B20+'Assumptions'!B21+'Assumptions'!B22+'Assumptions'!B23+'Assumptions'!B24+'Assumptions'!B25+'Assumptions'!B26) | W18: =-('Assumptions'!B18+'Assumptions'!B19+'Assumptions'!B20+'Assumptions'!B21+'Assumptions'!B22+'Assumptions'!B23+'Assumptions'!B24+'Assumptions'!B25+'Assumptions'!B26) | X18: =-('Assumptions'!B18+'Assumptions'!B19+'Assumptions'!B20+'Assumptions'!B21+'Assumptions'!B22+'Assumptions'!B23+'Assumptions'!B24+'Assumptions'!B25+'Assumptions'!B26) | Y18: =-('Assumptions'!B18+'Assumptions'!B19+'Assumptions'!B20+'Assumptions'!B21+'Assumptions'!B22+'Assumptions'!B23+'Assumptions'!B24+'Assumptions'!B25+'Assumptions'!B26)
A19: PROFIT
A20: Net profit / loss | B20: =B16+B18 | C20: =C16+C18 | D20: =D16+D18 | E20: =E16+E18 | F20: =F16+F18 | G20: =G16+G18 | H20: =H16+H18 | I20: =I16+I18 | ... Y20: =Y16+Y18
A21: Cumulative net profit | B21: =B20 | C21: =B21+C20 | D21: =C21+D20 | E21: =D21+E20 | F21: =E21+F20 | G21: =F21+G20 | H21: =G21+H20 | I21: =H21+I20 | J21: =I21+J20 | ... Y21: =X21+Y20
A22: MRR (net) | B22: =B16 | C22: =C16 | D22: =D16 | E22: =E16 | F22: =F16 | G22: =G16 | H22: =H16 | I22: =I16 | ... Y22: =Y16
A23: ARR run-rate | B23: =B22*12 | C23: =C22*12 | D23: =D22*12 | E23: =E22*12 | F23: =F22*12 | G23: =G22*12 | H23: =H22*12 | I23: =I22*12 | ... Y23: =Y22*12

Sheet Scenarios
A1: SOULGAINZ · Scenario Analysis (USD)
A2: Metric | B2: 🐻 BEAR | C2: 📊 BASE | D2: 🚀 BULL
A3: ASSUMPTIONS
A4: Month 1 signups | B4: 30 | C4: 80 | D4: 200
A5: Monthly signup growth (MoM) | B5: 0.05 | C5: 0.15 | D5: 0.3
A6: Free-to-paid conversion | B6: 0.02 | C6: 0.04 | D6: 0.06
A7: Monthly churn | B7: 0.1 | C7: 0.06 | D7: 0.04
A8: Monthly fixed costs (USD) | B8: 57.45 | C8: 57.45 | D8: 57.45
A9: AT 6 MONTHS
A10: Total paying users | B10: 8 | C10: 42 | D10: 130
A11: MRR net (USD) | B11: 60 | C11: 480 | D11: 1480
A12: ARR run-rate (USD) | B12: 720 | C12: 5760 | D12: 17760
A13: Net profit/loss (USD) | B13: -520 | C13: -90 | D13: 1422
A14: AT 12 MONTHS
A15: Total paying users | B15: 18 | C15: 105 | D15: 380
A16: MRR net (USD) | B16: 140 | C16: 1240 | D16: 4460
A17: ARR run-rate (USD) | B17: 1680 | C17: 14880 | D17: 53520
A18: Net profit/loss (USD) | B18: -460 | C18: 1183 | D18: 4403
A19: Cumulative profit/loss (USD) | B19: -4890 | C19: 2140 | D19: 29800
A20: AT 24 MONTHS
A21: Total paying users | B21: 30 | C21: 280 | D21: 1100
A22: MRR net (USD) | B22: 240 | C22: 3290 | D22: 13020
A23: ARR run-rate (USD) | B23: 2880 | C23: 39480 | D23: 156240
A24: Net profit/loss (USD) | B24: -290 | C24: 3233 | D24: 12963
A25: Cumulative profit/loss (USD) | B25: -7200 | C25: 19800 | D25: 142000
A26: Break-even month | B26: Never | C26: M11 | D26: M7
A27: UNIT ECONOMICS
A28: Blended ARPU/mo (USD) | B28: 10.8 | C28: 11.8 | D28: 12.3
A29: Est. blended LTV (USD) | B29: 108 | C29: 197 | D29: 308
A30: CAC (USD, est. $0 organic) | B30: 0 | C30: 0 | D30: 5
A31: Gross margin | B31: 0.92 | C31: 0.93 | D31: 0.94

Sheet P&L Summary
A1: SOULGAINZ · P&L Summary (USD, BASE CASE)
A2: Line Item | B2: Year 1 | C2: Year 2 (proj) | D2: Year 3 (proj)
A3: REVENUE
A4: Gross subscription revenue | B4: 7480 | C4: 37800 | D4: 95040
A5: Stripe processing fees | B5: -217 | C5: -1096 | D5: -2756
A6: Net revenue | B6: 7263 | C6: 36704 | D6: 92284
A7: Gross margin | B7: 0.971 | C7: 0.971 | D7: 0.971
A8: COSTS (USD/YR)
A9: Claude Pro subscription | B9: -230 | C9: -230 | D9: -230
A10: Netlify Pro | B10: -228 | C10: -228 | D10: -228
A11: Apple Developer Program | B11: -99 | C11: -99 | D11: -99
A12: Google Domains | B12: -12 | C12: -12 | D12: -12
A13: Misc / buffer | B13: -120 | C13: -120 | D13: -120
A14: Total fixed costs | B14: -689 | C14: -689 | D14: -689
A15: PROFITABILITY
A16: EBITDA | B16: 6574 | C16: 36015 | D16: 91595
A17: EBITDA margin | B17: 0.905 | C17: 0.982 | D17: 0.993
A18: Estimated tax @ 25% | B18: -1644 | C18: -9004 | D18: -22899
A19: Net profit (after est. tax) | B19: 4931 | C19: 27011 | D19: 68696
A20: Net margin | B20: 0.679 | C20: 0.736 | D20: 0.745
A21: RETURN ON INVESTMENT
A22: Cash out-of-pocket to date | B22: 136 | C22: 0 | D22: 0
A23: Sweat equity (est., not cash) | B23: 32000 | C23: 0 | D23: 0
A24: ROI on cash (Y1 net / $136) | B24: 36.2 | C24: 0 | D24: 0
A25: Paying users — year-end (est.) | B25: 105 | C25: 280 | D25: 650
A26: ARR at year-end (est., USD) | B26: 14880 | C26: 39480 | D26: 95040

Sheet Pending + Next Steps
A1: SOULGAINZ · Pending Tasks + Next Steps
A2: Task | B2: Status | C2: Notes
A3: GOOGLE PLAY
A4: Android device verification | B4: ⏳ WAITING | C4: Borrow any Android phone · sign into Play Console app
A5: Google identity verification | B5: ⏳ IN PROGRESS | C5: Google verifying docs · email in 1-3 days
A6: Create app in Play Console | B6: 🔒 BLOCKED | C6: Unblocks once identity + device verified
A7: Upload app-release.aab | B7: ✅ READY | C7: _mobile/android/app/build/outputs/bundle/release/
A8: Closed testing — 12+ testers, 14 days | B8: 🔒 BLOCKED | C8: Need 12 Android users · friends/family
A9: Fill store listing | B9: 📋 COPY READY | C9: STORE_LISTING_COPY.md · assets in _mobile/assets/
A10: Submit to Production | B10: 🔒 BLOCKED | C10: After 14-day closed test passes
A11: APPLE APP STORE
A12: Apple Developer enrollment | B12: ⏳ WAITING | C12: Call +1 800-275-2273 if online enrollment fails
A13: iOS build + Xcode archive | B13: 🔒 BLOCKED | C13: Needs enrollment approved first
A14: Upload to App Store Connect | B14: 🔒 BLOCKED | C14: After Xcode archive
A15: TestFlight beta + App Store review | B15: 🔒 BLOCKED | C15: Apple reviews take 1-7 days
A16: DOMAIN + SECURITY — DO THESE NOW
A17: Enable domain lock (Squarespace) | B17: ⚠️ DO NOW | C17: domains.squarespace.com → soulgainz.app → Security → Domain lock
A18: Verify WHOIS privacy is ON | B18: ⚠️ DO NOW | C18: domains.squarespace.com → Privacy → ON
A19: Enable DNSSEC | B19: ⚠️ SOON | C19: Squarespace Domains → Security → DNSSEC
A20: Enable 2FA on Squarespace + Netlify | B20: ⚠️ DO NOW | C20: Use Authenticator app
A21: Set up DKIM on Resend | B21: 🟡 SOON | C21: resend.com → Domains → verify soulgainz.app
A22: Add DMARC DNS record | B22: 🟡 SOON | C22: TXT _dmarc → v=DMARC1; p=quarantine; rua=mailto:support@soulgainz.com
A23: Register soulgainz.com + .co variants | B23: 🟡 SOON | C23: Prevent brand squatting · redirect to soulgainz.app
A24: File trademark — IP Australia (Class 41+42) | B24: 🟡 THIS QUARTER | C24: ipaustralia.gov.au · ~AUD $500 · self-file
A25: T&C + LIABILITY — STATUS
A26: T&C checkbox on signup | B26: ✅ DONE | C26: Required before account creation
A27: terms_accepted_at timestamp stored | B27: ✅ DONE | C27: Saved to Supabase user metadata on signup (Aug 2026)
A28: Health disclaimer + liability cap in terms | B28: ✅ DONE | C28: Added August 2026 — liability capped to 12-mo payments
A29: Add terms_accepted_at column to profiles table | B29: ⚠️ DO NOW | C29: Run SQL: ALTER TABLE profiles ADD COLUMN terms_accepted_at TIMESTAMPTZ
A30: Create standalone soulgainz.app/terms page | B30: 🟡 SOON | C30: Makes T&C legally defensible in court
A31: Register ABN or Pty Ltd | B31: 🟡 THIS QUARTER | C31: Pty Ltd recommended for liability protection · ~AUD $500
A32: MARKETING + GROWTH
A33: Back up keystore to iCloud | B33: ⚠️ URGENT | C33: Run: cp _mobile/soulgainz-release.keystore ~/Library/Mobile\ Documents/com~apple~CloudDocs/
A34: Run iCloud full sync | B34: ⚠️ DO NOW | C34: bash ~/Desktop/Cowork/SoulGainz/sync-to-icloud.sh
A35: Instagram content — next batch | B35: 📋 PENDING | C35: 4 posts done · continue social calendar
A36: Send launch email to waitlist | B36: 📋 PENDING | C36: Trigger Resend launch sequence
A37: Update paywall recipe count 94 → 173 | B37: 📋 PENDING | C37: index.html paywall card still shows 94
A38: Analytics setup (Plausible or GA4) | B38: 📋 PENDING | C38: Track signups, conversions, page views
