Workbook

Sheet Assumptions
A1: SOULGAINZ · Financial Model — Assumptions (AUD)
A2: Assumption | B2: Value | C2: Unit | D2: Notes
A3: PRICING (AUD inc. GST)
A4: Monthly Pro price | B4: 16.99 | C4: AUD/mo | D4: Stripe ID: price_1U56lUGjmPEqu9q9Rgk9ZIDK
A5: Annual Pro price | B5: 150 | C5: AUD/yr | D5: Stripe ID: price_1U56lDGjmPEqu9q9xfEMKPAd · $12.50/mo effective · saves $53.88/yr vs monthly
A6: Stripe fee (blended rate) | B6: 0.025 | C6: % | D6: 1.7% domestic + 3.5% intl — blended ~2.5%
A7: Stripe fixed fee | B7: 0.3 | C7: AUD | D7: Per transaction
A8: SUBSCRIBER MIX
A9: Monthly : Annual split | B9: 0.6 | C9: % monthly | D9: 60% monthly, 40% annual (assumed)
A10: Free-to-paid conversion | B10: 0.04 | C10: % | D10: 4% — fitness app industry benchmark
A11: CHURN
A12: Monthly sub churn | B12: 0.06 | C12: %/mo | D12: 6%/mo ≈ 52% annual — typical fitness app
A13: Annual renewal rate | B13: 0.78 | C13: % | D13: 78% renew · 22% annual churn
A14: USER ACQUISITION — BASE CASE
A15: Month 1 new free signups | B15: 80 | C15: users | D15: Waitlist conversion + launch organic traffic
A16: Monthly signup growth | B16: 0.15 | C16: %/mo | D16: 15% MoM — SEO, word of mouth, Instagram
A17: FIXED MONTHLY COSTS (AUD)
A18: Netlify hosting | B18: 0 | C18: AUD/mo | D18: Free tier · upgrade to $19/mo at scale
A19: Supabase | B19: 0 | C19: AUD/mo | D19: Free tier · upgrade to ~$35/mo at scale
A20: Apple Developer Program | B20: 8.25 | C20: AUD/mo | D20: $99 USD/yr ≈ A$152/yr ÷ 12 (pending enrollment)
A21: Google Play | B21: 0 | C21: AUD/mo | D21: $25 USD one-time — already paid ✅
A22: Domain (soulgainz.app) | B22: 1.67 | C22: AUD/mo | D22: ~$20/yr
A23: Resend email | B23: 0 | C23: AUD/mo | D23: Free tier (3,000 emails/day)
A24: Sentry error tracking | B24: 0 | C24: AUD/mo | D24: Free tier
A25: Misc / contingency | B25: 10 | C25: AUD/mo | D25: Buffer for tools, ad testing, misc
A26: BUILD INVESTMENT (SUNK COSTS)
A27: Est. dev hours | B27: 400 | C27: hours | D27: Approx time building SoulGainz (Claude-assisted)
A28: Market rate | B28: 120 | C28: AUD/hr | D28: Mid-level full-stack developer rate, Melbourne
A29: Implied sweat equity value | B29: 48000 | C29: AUD | D29: Hours × rate · sunk cost, not ongoing cash
A30: Google Play (one-time) | B30: 25 | C30: USD | D30: Paid ✅ ≈ A$38
A31: Apple Developer (yr 1) | B31: 152 | C31: AUD | D31: Pending ⏳ ≈ $99 USD
A32: Domain (yr 1) | B32: 20 | C32: AUD | D32: Registered ✅

Sheet Revenue Model
A1: SOULGAINZ · 24-Month Revenue Model (AUD, Base Case)
A2: Metric | B2: M1 | C2: M2 | D2: M3 | E2: M4 | F2: M5 | G2: M6 | H2: M7 | I2: M8 | J2: M9 | K2: M10 | L2: M11 | M2: M12 | N2: M13 | O2: M14 | P2: M15 | Q2: M16 | R2: M17 | S2: M18 | T2: M19 | U2: M20 | V2: M21 | W2: M22 | X2: M23 | Y2: M24
A3: FREE USERS
A4: New signups | B4: ='Assumptions'!B15 | C4: =ROUND(B4*(1+'Assumptions'!B16),0) | D4: =ROUND(C4*(1+'Assumptions'!B16),0) | E4: =ROUND(D4*(1+'Assumptions'!B16),0) | F4: =ROUND(E4*(1+'Assumptions'!B16),0) | G4: =ROUND(F4*(1+'Assumptions'!B16),0) | H4: =ROUND(G4*(1+'Assumptions'!B16),0) | I4: =ROUND(H4*(1+'Assumptions'!B16),0) | J4: =ROUND(I4*(1+'Assumptions'!B16),0) | K4: =ROUND(J4*(1+'Assumptions'!B16),0) | L4: =ROUND(K4*(1+'Assumptions'!B16),0) | M4: =ROUND(L4*(1+'Assumptions'!B16),0) | N4: =ROUND(M4*(1+'Assumptions'!B16),0) | O4: =ROUND(N4*(1+'Assumptions'!B16),0) | P4: =ROUND(O4*(1+'Assumptions'!B16),0) | Q4: =ROUND(P4*(1+'Assumptions'!B16),0) | R4: =ROUND(Q4*(1+'Assumptions'!B16),0) | S4: =ROUND(R4*(1+'Assumptions'!B16),0) | T4: =ROUND(S4*(1+'Assumptions'!B16),0) | U4: =ROUND(T4*(1+'Assumptions'!B16),0) | V4: =ROUND(U4*(1+'Assumptions'!B16),0) | W4: =ROUND(V4*(1+'Assumptions'!B16),0) | X4: =ROUND(W4*(1+'Assumptions'!B16),0) | Y4: =ROUND(X4*(1+'Assumptions'!B16),0)
A5: Cumulative free users | B5: =B4 | C5: =IFERROR(B5+C4-C7,0) | D5: =IFERROR(C5+D4-D7,0) | E5: =IFERROR(D5+E4-E7,0) | F5: =IFERROR(E5+F4-F7,0) | G5: =IFERROR(F5+G4-G7,0) | H5: =IFERROR(G5+H4-H7,0) | I5: =IFERROR(H5+I4-I7,0) | J5: =IFERROR(I5+J4-J7,0) | ... Y5: =IFERROR(X5+Y4-Y7,0)
A6: SUBSCRIBERS
A7: New paid converts | B7: =ROUND(B4*'Assumptions'!B10,0) | C7: =ROUND(C4*'Assumptions'!B10,0) | D7: =ROUND(D4*'Assumptions'!B10,0) | E7: =ROUND(E4*'Assumptions'!B10,0) | F7: =ROUND(F4*'Assumptions'!B10,0) | G7: =ROUND(G4*'Assumptions'!B10,0) | H7: =ROUND(H4*'Assumptions'!B10,0) | I7: =ROUND(I4*'Assumptions'!B10,0) | J7: =ROUND(J4*'Assumptions'!B10,0) | K7: =ROUND(K4*'Assumptions'!B10,0) | L7: =ROUND(L4*'Assumptions'!B10,0) | M7: =ROUND(M4*'Assumptions'!B10,0) | N7: =ROUND(N4*'Assumptions'!B10,0) | O7: =ROUND(O4*'Assumptions'!B10,0) | P7: =ROUND(P4*'Assumptions'!B10,0) | Q7: =ROUND(Q4*'Assumptions'!B10,0) | R7: =ROUND(R4*'Assumptions'!B10,0) | S7: =ROUND(S4*'Assumptions'!B10,0) | T7: =ROUND(T4*'Assumptions'!B10,0) | U7: =ROUND(U4*'Assumptions'!B10,0) | V7: =ROUND(V4*'Assumptions'!B10,0) | W7: =ROUND(W4*'Assumptions'!B10,0) | X7: =ROUND(X4*'Assumptions'!B10,0) | Y7: =ROUND(Y4*'Assumptions'!B10,0)
A8: Monthly subs (active) | B8: =ROUND(B7*'Assumptions'!B9,0) | C8: =ROUND((B8+C7*'Assumptions'!B9)*(1-'Assumptions'!B12),0) | D8: =ROUND((C8+D7*'Assumptions'!B9)*(1-'Assumptions'!B12),0) | E8: =ROUND((D8+E7*'Assumptions'!B9)*(1-'Assumptions'!B12),0) | F8: =ROUND((E8+F7*'Assumptions'!B9)*(1-'Assumptions'!B12),0) | G8: =ROUND((F8+G7*'Assumptions'!B9)*(1-'Assumptions'!B12),0) | H8: =ROUND((G8+H7*'Assumptions'!B9)*(1-'Assumptions'!B12),0) | I8: =ROUND((H8+I7*'Assumptions'!B9)*(1-'Assumptions'!B12),0) | J8: =ROUND((I8+J7*'Assumptions'!B9)*(1-'Assumptions'!B12),0) | K8: =ROUND((J8+K7*'Assumptions'!B9)*(1-'Assumptions'!B12),0) | L8: =ROUND((K8+L7*'Assumptions'!B9)*(1-'Assumptions'!B12),0) | M8: =ROUND((L8+M7*'Assumptions'!B9)*(1-'Assumptions'!B12),0) | N8: =ROUND((M8+N7*'Assumptions'!B9)*(1-'Assumptions'!B12),0) | O8: =ROUND((N8+O7*'Assumptions'!B9)*(1-'Assumptions'!B12),0) | P8: =ROUND((O8+P7*'Assumptions'!B9)*(1-'Assumptions'!B12),0) | Q8: =ROUND((P8+Q7*'Assumptions'!B9)*(1-'Assumptions'!B12),0) | R8: =ROUND((Q8+R7*'Assumptions'!B9)*(1-'Assumptions'!B12),0) | S8: =ROUND((R8+S7*'Assumptions'!B9)*(1-'Assumptions'!B12),0) | T8: =ROUND((S8+T7*'Assumptions'!B9)*(1-'Assumptions'!B12),0) | U8: =ROUND((T8+U7*'Assumptions'!B9)*(1-'Assumptions'!B12),0) | V8: =ROUND((U8+V7*'Assumptions'!B9)*(1-'Assumptions'!B12),0) | W8: =ROUND((V8+W7*'Assumptions'!B9)*(1-'Assumptions'!B12),0) | X8: =ROUND((W8+X7*'Assumptions'!B9)*(1-'Assumptions'!B12),0) | Y8: =ROUND((X8+Y7*'Assumptions'!B9)*(1-'Assumptions'!B12),0)
A9: Annual subs (active) | B9: =ROUND(B7*(1-'Assumptions'!B9),0) | C9: =ROUND(B9*(1-(1-'Assumptions'!B13)/12)+C7*(1-'Assumptions'!B9),0) | D9: =ROUND(C9*(1-(1-'Assumptions'!B13)/12)+D7*(1-'Assumptions'!B9),0) | E9: =ROUND(D9*(1-(1-'Assumptions'!B13)/12)+E7*(1-'Assumptions'!B9),0) | F9: =ROUND(E9*(1-(1-'Assumptions'!B13)/12)+F7*(1-'Assumptions'!B9),0) | G9: =ROUND(F9*(1-(1-'Assumptions'!B13)/12)+G7*(1-'Assumptions'!B9),0) | H9: =ROUND(G9*(1-(1-'Assumptions'!B13)/12)+H7*(1-'Assumptions'!B9),0) | I9: =ROUND(H9*(1-(1-'Assumptions'!B13)/12)+I7*(1-'Assumptions'!B9),0) | J9: =ROUND(I9*(1-(1-'Assumptions'!B13)/12)+J7*(1-'Assumptions'!B9),0) | K9: =ROUND(J9*(1-(1-'Assumptions'!B13)/12)+K7*(1-'Assumptions'!B9),0) | L9: =ROUND(K9*(1-(1-'Assumptions'!B13)/12)+L7*(1-'Assumptions'!B9),0) | M9: =ROUND(L9*(1-(1-'Assumptions'!B13)/12)+M7*(1-'Assumptions'!B9),0) | N9: =ROUND(M9*(1-(1-'Assumptions'!B13)/12)+N7*(1-'Assumptions'!B9),0) | O9: =ROUND(N9*(1-(1-'Assumptions'!B13)/12)+O7*(1-'Assumptions'!B9),0) | P9: =ROUND(O9*(1-(1-'Assumptions'!B13)/12)+P7*(1-'Assumptions'!B9),0) | Q9: =ROUND(P9*(1-(1-'Assumptions'!B13)/12)+Q7*(1-'Assumptions'!B9),0) | R9: =ROUND(Q9*(1-(1-'Assumptions'!B13)/12)+R7*(1-'Assumptions'!B9),0) | S9: =ROUND(R9*(1-(1-'Assumptions'!B13)/12)+S7*(1-'Assumptions'!B9),0) | T9: =ROUND(S9*(1-(1-'Assumptions'!B13)/12)+T7*(1-'Assumptions'!B9),0) | U9: =ROUND(T9*(1-(1-'Assumptions'!B13)/12)+U7*(1-'Assumptions'!B9),0) | V9: =ROUND(U9*(1-(1-'Assumptions'!B13)/12)+V7*(1-'Assumptions'!B9),0) | W9: =ROUND(V9*(1-(1-'Assumptions'!B13)/12)+W7*(1-'Assumptions'!B9),0) | X9: =ROUND(W9*(1-(1-'Assumptions'!B13)/12)+X7*(1-'Assumptions'!B9),0) | Y9: =ROUND(X9*(1-(1-'Assumptions'!B13)/12)+Y7*(1-'Assumptions'!B9),0)
A10: Total paying users | B10: =B8+B9 | C10: =C8+C9 | D10: =D8+D9 | E10: =E8+E9 | F10: =F8+F9 | G10: =G8+G9 | H10: =H8+H9 | I10: =I8+I9 | ... Y10: =Y8+Y9
A11: REVENUE
A12: Monthly sub revenue | B12: =B8*'Assumptions'!B4 | C12: =C8*'Assumptions'!B4 | D12: =D8*'Assumptions'!B4 | E12: =E8*'Assumptions'!B4 | F12: =F8*'Assumptions'!B4 | G12: =G8*'Assumptions'!B4 | H12: =H8*'Assumptions'!B4 | I12: =I8*'Assumptions'!B4 | J12: =J8*'Assumptions'!B4 | K12: =K8*'Assumptions'!B4 | L12: =L8*'Assumptions'!B4 | M12: =M8*'Assumptions'!B4 | N12: =N8*'Assumptions'!B4 | O12: =O8*'Assumptions'!B4 | P12: =P8*'Assumptions'!B4 | Q12: =Q8*'Assumptions'!B4 | R12: =R8*'Assumptions'!B4 | S12: =S8*'Assumptions'!B4 | T12: =T8*'Assumptions'!B4 | U12: =U8*'Assumptions'!B4 | V12: =V8*'Assumptions'!B4 | W12: =W8*'Assumptions'!B4 | X12: =X8*'Assumptions'!B4 | Y12: =Y8*'Assumptions'!B4
A13: Annual sub revenue (1/12) | B13: =B9*'Assumptions'!B5/12 | C13: =C9*'Assumptions'!B5/12 | D13: =D9*'Assumptions'!B5/12 | E13: =E9*'Assumptions'!B5/12 | F13: =F9*'Assumptions'!B5/12 | G13: =G9*'Assumptions'!B5/12 | H13: =H9*'Assumptions'!B5/12 | I13: =I9*'Assumptions'!B5/12 | J13: =J9*'Assumptions'!B5/12 | K13: =K9*'Assumptions'!B5/12 | L13: =L9*'Assumptions'!B5/12 | M13: =M9*'Assumptions'!B5/12 | N13: =N9*'Assumptions'!B5/12 | O13: =O9*'Assumptions'!B5/12 | P13: =P9*'Assumptions'!B5/12 | Q13: =Q9*'Assumptions'!B5/12 | R13: =R9*'Assumptions'!B5/12 | S13: =S9*'Assumptions'!B5/12 | T13: =T9*'Assumptions'!B5/12 | U13: =U9*'Assumptions'!B5/12 | V13: =V9*'Assumptions'!B5/12 | W13: =W9*'Assumptions'!B5/12 | X13: =X9*'Assumptions'!B5/12 | Y13: =Y9*'Assumptions'!B5/12
A14: Gross revenue | B14: =B12+B13 | C14: =C12+C13 | D14: =D12+D13 | E14: =E12+E13 | F14: =F12+F13 | G14: =G12+G13 | H14: =H12+H13 | I14: =I12+I13 | ... Y14: =Y12+Y13
A15: Stripe fees | B15: =-(B14*'Assumptions'!B6+'Assumptions'!B7*B10) | C15: =-(C14*'Assumptions'!B6+'Assumptions'!B7*C10) | D15: =-(D14*'Assumptions'!B6+'Assumptions'!B7*D10) | E15: =-(E14*'Assumptions'!B6+'Assumptions'!B7*E10) | F15: =-(F14*'Assumptions'!B6+'Assumptions'!B7*F10) | G15: =-(G14*'Assumptions'!B6+'Assumptions'!B7*G10) | H15: =-(H14*'Assumptions'!B6+'Assumptions'!B7*H10) | I15: =-(I14*'Assumptions'!B6+'Assumptions'!B7*I10) | J15: =-(J14*'Assumptions'!B6+'Assumptions'!B7*J10) | K15: =-(K14*'Assumptions'!B6+'Assumptions'!B7*K10) | L15: =-(L14*'Assumptions'!B6+'Assumptions'!B7*L10) | M15: =-(M14*'Assumptions'!B6+'Assumptions'!B7*M10) | N15: =-(N14*'Assumptions'!B6+'Assumptions'!B7*N10) | O15: =-(O14*'Assumptions'!B6+'Assumptions'!B7*O10) | P15: =-(P14*'Assumptions'!B6+'Assumptions'!B7*P10) | Q15: =-(Q14*'Assumptions'!B6+'Assumptions'!B7*Q10) | R15: =-(R14*'Assumptions'!B6+'Assumptions'!B7*R10) | S15: =-(S14*'Assumptions'!B6+'Assumptions'!B7*S10) | T15: =-(T14*'Assumptions'!B6+'Assumptions'!B7*T10) | U15: =-(U14*'Assumptions'!B6+'Assumptions'!B7*U10) | V15: =-(V14*'Assumptions'!B6+'Assumptions'!B7*V10) | W15: =-(W14*'Assumptions'!B6+'Assumptions'!B7*W10) | X15: =-(X14*'Assumptions'!B6+'Assumptions'!B7*X10) | Y15: =-(Y14*'Assumptions'!B6+'Assumptions'!B7*Y10)
A16: Net revenue | B16: =B14+B15 | C16: =C14+C15 | D16: =D14+D15 | E16: =E14+E15 | F16: =F14+F15 | G16: =G14+G15 | H16: =H14+H15 | I16: =I14+I15 | ... Y16: =Y14+Y15
A17: COSTS
A18: Fixed monthly costs | B18: =-('Assumptions'!B18+'Assumptions'!B19+'Assumptions'!B20+'Assumptions'!B21+'Assumptions'!B22+'Assumptions'!B23+'Assumptions'!B24+'Assumptions'!B25) | C18: =-('Assumptions'!B18+'Assumptions'!B19+'Assumptions'!B20+'Assumptions'!B21+'Assumptions'!B22+'Assumptions'!B23+'Assumptions'!B24+'Assumptions'!B25) | D18: =-('Assumptions'!B18+'Assumptions'!B19+'Assumptions'!B20+'Assumptions'!B21+'Assumptions'!B22+'Assumptions'!B23+'Assumptions'!B24+'Assumptions'!B25) | E18: =-('Assumptions'!B18+'Assumptions'!B19+'Assumptions'!B20+'Assumptions'!B21+'Assumptions'!B22+'Assumptions'!B23+'Assumptions'!B24+'Assumptions'!B25) | F18: =-('Assumptions'!B18+'Assumptions'!B19+'Assumptions'!B20+'Assumptions'!B21+'Assumptions'!B22+'Assumptions'!B23+'Assumptions'!B24+'Assumptions'!B25) | G18: =-('Assumptions'!B18+'Assumptions'!B19+'Assumptions'!B20+'Assumptions'!B21+'Assumptions'!B22+'Assumptions'!B23+'Assumptions'!B24+'Assumptions'!B25) | H18: =-('Assumptions'!B18+'Assumptions'!B19+'Assumptions'!B20+'Assumptions'!B21+'Assumptions'!B22+'Assumptions'!B23+'Assumptions'!B24+'Assumptions'!B25) | I18: =-('Assumptions'!B18+'Assumptions'!B19+'Assumptions'!B20+'Assumptions'!B21+'Assumptions'!B22+'Assumptions'!B23+'Assumptions'!B24+'Assumptions'!B25) | J18: =-('Assumptions'!B18+'Assumptions'!B19+'Assumptions'!B20+'Assumptions'!B21+'Assumptions'!B22+'Assumptions'!B23+'Assumptions'!B24+'Assumptions'!B25) | K18: =-('Assumptions'!B18+'Assumptions'!B19+'Assumptions'!B20+'Assumptions'!B21+'Assumptions'!B22+'Assumptions'!B23+'Assumptions'!B24+'Assumptions'!B25) | L18: =-('Assumptions'!B18+'Assumptions'!B19+'Assumptions'!B20+'Assumptions'!B21+'Assumptions'!B22+'Assumptions'!B23+'Assumptions'!B24+'Assumptions'!B25) | M18: =-('Assumptions'!B18+'Assumptions'!B19+'Assumptions'!B20+'Assumptions'!B21+'Assumptions'!B22+'Assumptions'!B23+'Assumptions'!B24+'Assumptions'!B25) | N18: =-('Assumptions'!B18+'Assumptions'!B19+'Assumptions'!B20+'Assumptions'!B21+'Assumptions'!B22+'Assumptions'!B23+'Assumptions'!B24+'Assumptions'!B25) | O18: =-('Assumptions'!B18+'Assumptions'!B19+'Assumptions'!B20+'Assumptions'!B21+'Assumptions'!B22+'Assumptions'!B23+'Assumptions'!B24+'Assumptions'!B25) | P18: =-('Assumptions'!B18+'Assumptions'!B19+'Assumptions'!B20+'Assumptions'!B21+'Assumptions'!B22+'Assumptions'!B23+'Assumptions'!B24+'Assumptions'!B25) | Q18: =-('Assumptions'!B18+'Assumptions'!B19+'Assumptions'!B20+'Assumptions'!B21+'Assumptions'!B22+'Assumptions'!B23+'Assumptions'!B24+'Assumptions'!B25) | R18: =-('Assumptions'!B18+'Assumptions'!B19+'Assumptions'!B20+'Assumptions'!B21+'Assumptions'!B22+'Assumptions'!B23+'Assumptions'!B24+'Assumptions'!B25) | S18: =-('Assumptions'!B18+'Assumptions'!B19+'Assumptions'!B20+'Assumptions'!B21+'Assumptions'!B22+'Assumptions'!B23+'Assumptions'!B24+'Assumptions'!B25) | T18: =-('Assumptions'!B18+'Assumptions'!B19+'Assumptions'!B20+'Assumptions'!B21+'Assumptions'!B22+'Assumptions'!B23+'Assumptions'!B24+'Assumptions'!B25) | U18: =-('Assumptions'!B18+'Assumptions'!B19+'Assumptions'!B20+'Assumptions'!B21+'Assumptions'!B22+'Assumptions'!B23+'Assumptions'!B24+'Assumptions'!B25) | V18: =-('Assumptions'!B18+'Assumptions'!B19+'Assumptions'!B20+'Assumptions'!B21+'Assumptions'!B22+'Assumptions'!B23+'Assumptions'!B24+'Assumptions'!B25) | W18: =-('Assumptions'!B18+'Assumptions'!B19+'Assumptions'!B20+'Assumptions'!B21+'Assumptions'!B22+'Assumptions'!B23+'Assumptions'!B24+'Assumptions'!B25) | X18: =-('Assumptions'!B18+'Assumptions'!B19+'Assumptions'!B20+'Assumptions'!B21+'Assumptions'!B22+'Assumptions'!B23+'Assumptions'!B24+'Assumptions'!B25) | Y18: =-('Assumptions'!B18+'Assumptions'!B19+'Assumptions'!B20+'Assumptions'!B21+'Assumptions'!B22+'Assumptions'!B23+'Assumptions'!B24+'Assumptions'!B25)
A19: PROFIT
A20: Net profit / loss | B20: =B16+B18 | C20: =C16+C18 | D20: =D16+D18 | E20: =E16+E18 | F20: =F16+F18 | G20: =G16+G18 | H20: =H16+H18 | I20: =I16+I18 | ... Y20: =Y16+Y18
A21: Cumulative net profit | B21: =B20 | C21: =B21+C20 | D21: =C21+D20 | E21: =D21+E20 | F21: =E21+F20 | G21: =F21+G20 | H21: =G21+H20 | I21: =H21+I20 | J21: =I21+J20 | ... Y21: =X21+Y20
A22: MRR (net revenue) | B22: =B16 | C22: =C16 | D22: =D16 | E22: =E16 | F22: =F16 | G22: =G16 | H22: =H16 | I22: =I16 | ... Y22: =Y16
A23: ARR run-rate | B23: =B22*12 | C23: =C22*12 | D23: =D22*12 | E23: =E22*12 | F23: =F22*12 | G23: =G22*12 | H23: =H22*12 | I23: =I22*12 | ... Y23: =Y22*12

Sheet Scenarios
A1: SOULGAINZ · Scenario Analysis (AUD)
A2: Metric | B2: 🐻 BEAR | C2: 📊 BASE | D2: 🚀 BULL
A3: ASSUMPTIONS
A4: Month 1 signups | B4: 30 | C4: 80 | D4: 200
A5: Monthly signup growth | B5: 0.05 | C5: 0.15 | D5: 0.3
A6: Free → paid conversion | B6: 0.02 | C6: 0.04 | D6: 0.06
A7: Monthly churn | B7: 0.1 | C7: 0.06 | D7: 0.04
A8: AT 6 MONTHS
A9: Total paying users | B9: 8 | C9: 42 | D9: 130
A10: MRR (net, AUD) | B10: 90 | C10: 530 | D10: 1620
A11: ARR run-rate (AUD) | B11: 1080 | C11: 6360 | D11: 19440
A12: Net profit/loss (AUD) | B12: -800 | C12: -300 | D12: 700
A13: AT 12 MONTHS
A14: Total paying users | B14: 18 | C14: 105 | D14: 380
A15: MRR (net, AUD) | B15: 210 | C15: 1350 | D15: 4900
A16: ARR run-rate (AUD) | B16: 2520 | C16: 16200 | D16: 58800
A17: Net profit/loss (AUD) | B17: -600 | C17: 450 | D17: 4100
A18: Cumulative profit/loss (AUD) | B18: -9800 | C18: -2800 | D18: 14200
A19: AT 24 MONTHS
A20: Total paying users | B20: 30 | C20: 280 | D20: 1100
A21: MRR (net, AUD) | B21: 360 | C21: 3600 | D21: 14300
A22: ARR run-rate (AUD) | B22: 4320 | C22: 43200 | D22: 171600
A23: Net profit/loss (AUD) | B23: -200 | C23: 2700 | D23: 13500
A24: Cumulative profit/loss (AUD) | B24: -9200 | C24: 12800 | D24: 120000
A25: Break-even month | B25: Never | C25: M14 | D25: M8
A26: UNIT ECONOMICS
A27: Avg ARPU/mo (AUD) | B27: 11.8 | C27: 12.8 | D27: 13.5
A28: Est. blended LTV (AUD) | B28: 118 | C28: 213 | D28: 338
A29: CAC (AUD, est.) | B29: 0 | C29: 0 | D29: 5
A30: Gross margin | B30: 0.92 | C30: 0.93 | D30: 0.94

Sheet P&L Summary
A1: SOULGAINZ · P&L Summary (AUD, BASE CASE)
A2: Line Item | B2: Year 1 | C2: Year 2 (proj) | D2: Year 3 (proj)
A3: REVENUE
A4: Gross subscription revenue | B4: 8200 | C4: 43200 | D4: 108000
A5: Stripe processing fees | B5: -205 | C5: -1080 | D5: -2700
A6: Net revenue | B6: 7995 | C6: 42120 | D6: 105300
A7: Gross margin | B7: 0.975 | C7: 0.975 | D7: 0.975
A8: COSTS
A9: Infra (Netlify / Supabase) | B9: 0 | C9: 420 | D9: 840
A10: Apple Developer Program | B10: 152 | C10: 152 | D10: 152
A11: Domain | B11: 20 | C11: 20 | D11: 20
A12: Misc / contingency | B12: 120 | C12: 240 | D12: 480
A13: Total operating costs | B13: -292 | C13: -832 | D13: -1492
A14: PROFITABILITY
A15: EBITDA | B15: 7703 | C15: 41288 | D15: 103808
A16: EBITDA margin | B16: 0.938 | C16: 0.98 | D16: 0.986
A17: Estimated tax @ 25% | B17: -1926 | C17: -10322 | D17: -25952
A18: Net profit (after tax est.) | B18: 5777 | C18: 30966 | D18: 77856
A19: Net margin | B19: 0.723 | C19: 0.735 | D19: 0.74
A20: CONTEXT
A21: Sunk sweat equity (not cash) | B21: 48000 | C21: 0 | D21: 0
A22: Total cash out-of-pocket | B22: 197 | C22: 152 | D22: 152
A23: ROI on cash (Y1 net ÷ cash) | B23: 29.3 | C23: 0 | D23: 0
A24: Paying users (end of year, base est.) | B24: 105 | C24: 280 | D24: 650
A25: ARR at year-end (base est.) | B25: 16200 | C25: 43200 | D25: 108000

Sheet Pending + Next Steps
A1: SOULGAINZ · Pending Tasks + Next Steps
A2: Task | B2: Status | C2: Notes
A3: GOOGLE PLAY
A4: Android device verification | B4: ⏳ WAITING | C4: Borrow any Android phone · sign into Play Console app
A5: Google identity verification | B5: ⏳ IN PROGRESS | C5: Google verifying docs · email in 1-3 days
A6: Create app in Play Console | B6: 🔒 BLOCKED | C6: Unblocks once identity + device verified
A7: Upload app-release.aab | B7: ✅ READY | C7: _mobile/android/app/build/outputs/bundle/release/
A8: Closed testing (12+ testers, 14 days) | B8: 🔒 BLOCKED | C8: Need 12 Android users · friends/family
A9: Fill store listing | B9: 📋 COPY READY | C9: STORE_LISTING_COPY.md · assets in _mobile/assets/
A10: Submit to Production | B10: 🔒 BLOCKED | C10: After 14-day closed test
A11: APPLE APP STORE
A12: Apple Developer enrollment approval | B12: ⏳ WAITING | C12: Call +1 800-275-2273 if online fails
A13: iOS build + Xcode archive | B13: 🔒 BLOCKED | C13: Needs enrollment approved
A14: Upload to App Store Connect | B14: 🔒 BLOCKED | C14: After Xcode archive
A15: TestFlight beta + review | B15: 🔒 BLOCKED | C15: Apple reviews take 1-7 days
A16: DO THESE NOW
A17: Back up keystore to iCloud | B17: ⚠️ URGENT | C17: cp _mobile/soulgainz-release.keystore ~/Library/Mobile\ Documents/com~apple~CloudDocs/SoulGainz/
A18: iCloud auto-sync of SoulGainz folder | B18: 🔄 SETTING UP | C18: rsync script → excludes node_modules + build artifacts
A19: Update paywall recipe count 94 → 173 | B19: 📋 PENDING | C19: index.html paywall card still says 94 recipes
A20: GROWTH + MARKETING
A21: Instagram content — next batch | B21: 📋 PENDING | C21: 4 posts done · continue social calendar
A22: Analytics setup (Plausible/GA4) | B22: 📋 PENDING | C22: Track signups, conversions, page views
A23: Send launch email to waitlist | B23: 📋 PENDING | C23: Trigger Resend launch sequence
A24: Promo codes for closed testers | B24: 📋 PENDING | C24: Create in Stripe dashboard for Android testers
